sdk_creator/__init__.py
sdk_creator/_models.py
sdk_creator/_typing.py
sdk_creator/adapter.py
sdk_creator/errors.py
sdk_creator/toolkit.py
sdk_creator-0.0.2.dist-info/METADATA
sdk_creator-0.0.2.dist-info/WHEEL
sdk_creator-0.0.2.dist-info/licenses/LICENSE
sdk_creator-0.0.2.dist-info/RECORD
