Metadata-Version: 2.4
Name: sdk-creator
Version: 0.0.2
Summary: A dead simple asynchronous wrapper for RESTful APIs
Project-URL: Homepage, https://github.com/mghalix/sdk-creator
Project-URL: Documentation, https://github.com/mghalix/sdk-creator#readme
Project-URL: Issues, https://github.com/mghalix/sdk-creator/issues
Project-URL: Respository, https://github.com/mghalix/sdk-creator.git
Project-URL: Changelog, https://github.com/mghalix/sdk-creator/blob/main/release-notes.md
Author-email: Mohanad Ghali <mghalix@gmail.com>
License: MIT
License-File: LICENSE
Classifier: Framework :: Pydantic :: 2
Classifier: Intended Audience :: Developers
Classifier: Intended Audience :: Information Technology
Classifier: Intended Audience :: System Administrators
Classifier: License :: OSI Approved :: MIT License
Classifier: Operating System :: OS Independent
Classifier: Programming Language :: Python
Classifier: Programming Language :: Python :: 3
Classifier: Programming Language :: Python :: 3 :: Only
Classifier: Programming Language :: Python :: 3.11
Classifier: Programming Language :: Python :: 3.12
Classifier: Programming Language :: Python :: 3.13
Classifier: Topic :: Internet
Classifier: Topic :: Software Development
Classifier: Topic :: Software Development :: Libraries
Classifier: Topic :: Software Development :: Libraries :: Application Frameworks
Classifier: Topic :: Software Development :: Libraries :: Python Modules
Classifier: Typing :: Typed
Requires-Python: >=3.11
Requires-Dist: httpx>=0.28.1
Requires-Dist: loguru>=0.7.3
Requires-Dist: pydantic>=2.11.7
